pywikibot_scripts
