Metadata-Version: 2.4
Name: pywikibot-scripts
Version: 10.3.0
Summary: Pywikibot Scripts Collection
Author-email: xqt <info@gno.de>
Maintainer-email: The Pywikibot team <pywikibot@lists.wikimedia.org>
License: MIT License
Project-URL: Homepage, https://www.mediawiki.org/wiki/Manual:Pywikibot
Project-URL: Documentation, https://doc.wikimedia.org/pywikibot/stable/
Project-URL: Repository, https://gerrit.wikimedia.org/r/plugins/gitiles/pywikibot/core/
Project-URL: GitHub Mirror, https://github.com/wikimedia/pywikibot
Project-URL: Download, https://www.pywikibot.org
Project-URL: Changelog, https://doc.wikimedia.org/pywikibot/master/changelog.html
Project-URL: Tracker, https://phabricator.wikimedia.org/tag/pywikibot/
Keywords: add text,archivebot,basic,bot,client,framework,mediawiki,pwb,pybot,python,pywiki,pywikibase,pywikibot,pywikipedia,pywikipediabot,replace,redirect,script,scripts,upload,wiki,wikibase,wikidata,wikimedia,wikipedia
Classifier: Development Status :: 5 - Production/Stable
Classifier: Environment :: Console
Classifier: Intended Audience :: Developers
Classifier: License :: OSI Approved :: MIT License
Classifier: Natural Language :: Afrikaans
Classifier: Natural Language :: Arabic
Classifier: Natural Language :: Basque
Classifier: Natural Language :: Bengali
Classifier: Natural Language :: Bosnian
Classifier: Natural Language :: Bulgarian
Classifier: Natural Language :: Cantonese
Classifier: Natural Language :: Catalan
Classifier: Natural Language :: Chinese (Simplified)
Classifier: Natural Language :: Chinese (Traditional)
Classifier: Natural Language :: Croatian
Classifier: Natural Language :: Czech
Classifier: Natural Language :: Danish
Classifier: Natural Language :: Dutch
Classifier: Natural Language :: English
Classifier: Natural Language :: Esperanto
Classifier: Natural Language :: Finnish
Classifier: Natural Language :: French
Classifier: Natural Language :: Galician
Classifier: Natural Language :: German
Classifier: Natural Language :: Greek
Classifier: Natural Language :: Hebrew
Classifier: Natural Language :: Hindi
Classifier: Natural Language :: Hungarian
Classifier: Natural Language :: Icelandic
Classifier: Natural Language :: Indonesian
Classifier: Natural Language :: Irish
Classifier: Natural Language :: Italian
Classifier: Natural Language :: Japanese
Classifier: Natural Language :: Javanese
Classifier: Natural Language :: Korean
Classifier: Natural Language :: Latin
Classifier: Natural Language :: Latvian
Classifier: Natural Language :: Lithuanian
Classifier: Natural Language :: Macedonian
Classifier: Natural Language :: Malay
Classifier: Natural Language :: Marathi
Classifier: Natural Language :: Nepali
Classifier: Natural Language :: Norwegian
Classifier: Natural Language :: Panjabi
Classifier: Natural Language :: Persian
Classifier: Natural Language :: Polish
Classifier: Natural Language :: Portuguese
Classifier: Natural Language :: Portuguese (Brazilian)
Classifier: Natural Language :: Romanian
Classifier: Natural Language :: Russian
Classifier: Natural Language :: Serbian
Classifier: Natural Language :: Slovak
Classifier: Natural Language :: Slovenian
Classifier: Natural Language :: Spanish
Classifier: Natural Language :: Swedish
Classifier: Natural Language :: Tamil
Classifier: Natural Language :: Telugu
Classifier: Natural Language :: Thai
Classifier: Natural Language :: Tibetan
Classifier: Natural Language :: Turkish
Classifier: Natural Language :: Ukrainian
Classifier: Natural Language :: Urdu
Classifier: Natural Language :: Vietnamese
Classifier: Operating System :: OS Independent
Classifier: Programming Language :: Python
Classifier: Programming Language :: Python :: 3
Classifier: Programming Language :: Python :: 3 :: Only
Classifier: Programming Language :: Python :: Implementation :: CPython
Classifier: Programming Language :: Python :: Implementation :: PyPy
Classifier: Topic :: Internet :: WWW/HTTP :: Dynamic Content :: Wiki
Classifier: Topic :: Software Development :: Libraries :: Python Modules
Classifier: Topic :: Utilities
Requires-Python: >=3.8.0
License-File: LICENSE
License-File: AUTHORS.rst
Requires-Dist: pywikibot>=10.2.0
Requires-Dist: isbnlib
Requires-Dist: langdetect
Requires-Dist: mwparserfromhell
Requires-Dist: pydot
Requires-Dist: unidecode
Dynamic: license-file
